{"author":{"id":"U_kgDODDLjfA","is_bot":false,"login":"motoo42","name":""},"body":"﻿## 배경\n현재 이적시장은 선수의 기존 지위와 제안받는 역할의 차이를 충분히 반영하지 못한다. 현실적으로 1군 주전 선수가 2군 제안을 받으면 대부분 거절하고, 2군 선수가 1군 제안을 받으면 낮은 금액에도 긍정적으로 반응할 가능성이 높다.\n\n## 요구사항\n- 선수의 기존 지위와 제안 역할을 비교해 최소 수락선을 다르게 계산한다.\n  - 기존 1군 주전 -> 2군 제안: 강한 거절 경향, 최소 수락선 상승\n  - 기존 1군 주전 -> 식스맨 제안: 소폭 거절 경향, 최소 수락선 상승\n  - 기존 2군 -> 1군 주전 제안: 강한 긍정 반응, 최소 수락선 하락\n  - 기존 2군 -> 식스맨 제안: 긍정 반응, 최소 수락선 하락\n- 구현 난도가 높다면 최소한 위 케이스를 강한 제약조건으로라도 반영한다.\n- 협상 분위기에도 역할 변화 효과가 즉시 반영되어야 한다.\n- AI 제안과 유저 제안의 수락선 계산은 서로 독립적으로 유지한다.\n\n## 완료 기준\n- 1군 주전에게 2군 제안을 하면 웬만해서 수락하지 않는다.\n- 2군 선수에게 1군/식스맨 제안을 하면 같은 금액이라도 분위기가 좋아진다.\n- 역할 차이에 따른 수락선 변화가 테스트로 검증된다.\n- 협상 UI에서 역할 변경 시 분위기 변화가 즉시 보인다.\r\n","closedAt":"2026-06-12T12:45:25Z","comments":[],"createdAt":"2026-06-10T11:33:01Z","labels":[{"id":"LA_kwDOSs5-Lc8AAAAClblJrw","name":"enhancement","description":"New feature or request","color":"a2eeef"},{"id":"LA_kwDOSs5-Lc8AAAACms1UPQ","name":"important","description":"긴급하진 않지만 프로젝트를 위해 꼭 해야 하는 일","color":"fef2c0"},{"id":"LA_kwDOSs5-Lc8AAAACms1cJg","name":"todo","description":"가까운 시일 내에 개발 착수 예정","color":"0e5f79"}],"number":43,"state":"CLOSED","title":"스토브리그 제안 역할별 수락선/거절 기준 강화","url":"https://github.com/boostcampwm-snu-2026-1/esports-manager-lite-motoo42/issues/43"}
